{
  "code": 20000,
  "name": "success",
  "message": "请求成功",
  "data": {
    "data": [
      {
        "id": "1429340",
        "mallType": "WD",
        "itemId": "7238095273",
        "title": "AQ9129-001",
        "picUrl": "https://cdn.findqc.com/item/20250530/mb9vzbci_e0w8.jpg",
        "price": "¥300.00",
        "toPrice": "$47.17",
        "status": "normal",
        "shopInfo": {
          "id": "160885222",
          "name": "Budgetshoes",
          "logo": "https://si.geilicdn.com/vshop-shop-logo-default.jpg?w=250&amp;h=250&amp;cp=1",
          "type": "WD"
        },
        "categoryId": 13,
        "qcPicCnt": 15,
        "qcVideoCnt": 0
      },
      {
        "id": "1393780",
        "mallType": "WD",
        "itemId": "7456250751",
        "title": "New Fashion Versatile Trendy Shoes -008",
        "picUrl": "https://cdn.findqc.com/item/20250711/mcxslcip_om1b.jpg",
        "price": "¥79.00",
        "toPrice": "$12.42",
        "status": "normal",
        "shopInfo": {
          "id": "1848876445",
          "name": "TrendyU",
          "logo": "https://si.geilicdn.com/wdseller1951015104-648400000196729261ae0a2315ef_250_250.jpg?w=250&amp;h=250&amp;cp=1",
          "type": "WD"
        },
        "categoryId": 0,
        "qcPicCnt": 137,
        "qcVideoCnt": 0
      },
      {
        "id": "1380429",
        "mallType": "WD",
        "itemId": "7237786727",
        "title": "DH7561-104",
        "picUrl": "https://cdn.findqc.com/item/20250522/mayco9ie_vo71.jpg",
        "price": "¥180.00",
        "toPrice": "$28.30",
        "status": "normal",
        "shopInfo": {
          "id": "160885222",
          "name": "Budgetshoes",
          "logo": "https://si.geilicdn.com/vshop-shop-logo-default.jpg?w=250&amp;h=250&amp;cp=1",
          "type": "WD"
        },
        "categoryId": 13,
        "qcPicCnt": 7,
        "qcVideoCnt": 0
      },
      {
        "id": "1318276",
        "mallType": "WD",
        "itemId": "7237949981",
        "title": "CU1726-100",
        "picUrl": "https://cdn.findqc.com/item/20250508/maf7g8p0_0i4n.jpg",
        "price": "¥199.00",
        "toPrice": "$31.29",
        "status": "normal",
        "shopInfo": {
          "id": "160885222",
          "name": "Budgetshoes",
          "logo": "https://si.geilicdn.com/vshop-shop-logo-default.jpg?w=250&amp;h=250&amp;cp=1",
          "type": "WD"
        },
        "categoryId": 0,
        "qcPicCnt": 7,
        "qcVideoCnt": 0
      },
      {
        "id": "1304595",
        "mallType": "WD",
        "itemId": "7239056396",
        "title": "DD1391-100",
        "picUrl": "https://cdn.findqc.com/item/20250506/mabl1vh5_gluw.jpg",
        "price": "¥165.00",
        "toPrice": "$25.95",
        "status": "normal",
        "shopInfo": {
          "id": "160885222",
          "name": "Budgetshoes",
          "logo": "https://si.geilicdn.com/vshop-shop-logo-default.jpg?w=250&amp;h=250&amp;cp=1",
          "type": "WD"
        },
        "categoryId": 13,
        "qcPicCnt": 7,
        "qcVideoCnt": 0
      },
      {
        "id": "1237306",
        "mallType": "WD",
        "itemId": "7290151908",
        "title": "NB Factory【NB530】",
        "picUrl": "https://cdn.findqc.com/item/20250605/mbirb04p_j36m.jpg",
        "price": "¥320.00",
        "toPrice": "$50.32",
        "status": "normal",
        "shopInfo": {
          "id": "1614216041",
          "name": "Cool Kicks",
          "logo": "https://si.geilicdn.com/wdseller1833424671-32e40000018d69a4252f0a21146b_250_250.jpg?w=250&amp;h=250&amp;cp=1",
          "type": "WD"
        },
        "categoryId": 13,
        "qcPicCnt": 8,
        "qcVideoCnt": 1
      },
      {
        "id": "1195362",
        "mallType": "WD",
        "itemId": "7243272742",
        "title": "White FX5398",
        "picUrl": "https://cdn.findqc.com/item/20250419/m9n427zz_e43t.jpg",
        "price": "¥198.00",
        "toPrice": "$31.13",
        "status": "normal",
        "shopInfo": {
          "id": "160885222",
          "name": "Budgetshoes",
          "logo": "https://si.geilicdn.com/vshop-shop-logo-default.jpg?w=250&amp;h=250&amp;cp=1",
          "type": "WD"
        },
        "categoryId": 0,
        "qcPicCnt": 16,
        "qcVideoCnt": 0
      },
      {
        "id": "1055272",
        "mallType": "WD",
        "itemId": "7238928002",
        "title": "FD4203-211",
        "picUrl": "https://cdn.findqc.com/item/20250327/m8q7219h_yid8.jpg",
        "price": "¥199.00",
        "toPrice": "$31.29",
        "status": "normal",
        "shopInfo": {
          "id": "160885222",
          "name": "Budgetshoes",
          "logo": "https://si.geilicdn.com/vshop-shop-logo-default.jpg?w=250&amp;h=250&amp;cp=1",
          "type": "WD"
        },
        "categoryId": 13,
        "qcPicCnt": 21,
        "qcVideoCnt": 0
      },
      {
        "id": "999328",
        "mallType": "WD",
        "itemId": "7226092971",
        "title": "【FK version】Top ceiling quality J0rdan 1 TS X A*J1 Low Travis Scott co-branded Barbell low-tops",
        "picUrl": "https://cdn.findqc.com/item/20250319/m8f34eua_wm5h.jpg",
        "price": "¥360.00",
        "toPrice": "$56.61",
        "status": "normal",
        "shopInfo": {
          "id": "1812255049",
          "name": "888VIP-SNKRS",
          "logo": "https://si.geilicdn.com/pcdecorate1816621089-76180000018cef01570f0a239737-unadjust_750_750.png?w=250&amp;h=250&amp;cp=1",
          "type": "WD"
        },
        "categoryId": 13,
        "qcPicCnt": 7,
        "qcVideoCnt": 0
      },
      {
        "id": "929279",
        "mallType": "WD",
        "itemId": "7258324811",
        "title": "1 Fashion shoes",
        "picUrl": "https://cdn.findqc.com/item/20250303/m7rwlgnk_kblq.jpg",
        "price": "¥190.00",
        "toPrice": "$29.88",
        "status": "normal",
        "shopInfo": {
          "id": "1832710585",
          "name": "Milan Shoes &amp; Clothing",
          "logo": "https://si.geilicdn.com/shopedit1857988414-4cf60000019a307f5d090a23047e-unadjust_750_750.png?w=250&amp;h=250&amp;cp=1",
          "type": "WD"
        },
        "categoryId": 13,
        "qcPicCnt": 28,
        "qcVideoCnt": 0
      },
      {
        "id": "886466",
        "mallType": "WD",
        "itemId": "7343845978",
        "title": "1 Low",
        "picUrl": "https://cdn.findqc.com/item/20250226/m7kzwomp_aqrs.jpg",
        "price": "¥130.00",
        "toPrice": "$20.44",
        "status": "normal",
        "shopInfo": {
          "id": "160885222",
          "name": "Budgetshoes",
          "logo": "https://si.geilicdn.com/vshop-shop-logo-default.jpg?w=250&amp;h=250&amp;cp=1",
          "type": "WD"
        },
        "categoryId": 13,
        "qcPicCnt": 195,
        "qcVideoCnt": 0
      },
      {
        "id": "476280",
        "mallType": "WD",
        "itemId": "7237955597",
        "title": " 315122-111",
        "picUrl": "https://cdn.findqc.com/item/20250217/m78hzeat_pz60.jpg",
        "price": "¥180.00",
        "toPrice": "$28.30",
        "status": "normal",
        "shopInfo": {
          "id": "160885222",
          "name": "Budgetshoes",
          "logo": "https://si.geilicdn.com/vshop-shop-logo-default.jpg?w=250&amp;h=250&amp;cp=1",
          "type": "WD"
        },
        "categoryId": 13,
        "qcPicCnt": 14,
        "qcVideoCnt": 0
      },
      {
        "id": "401560",
        "mallType": "WD",
        "itemId": "7237949979",
        "title": "DD1391-103",
        "picUrl": "https://cdn.findqc.com/item/20250330/m8vreheo_2f5w.jpg",
        "price": "¥199.00",
        "toPrice": "$31.29",
        "status": "normal",
        "shopInfo": {
          "id": "160885222",
          "name": "Budgetshoes",
          "logo": "https://si.geilicdn.com/vshop-shop-logo-default.jpg?w=250&amp;h=250&amp;cp=1",
          "type": "WD"
        },
        "categoryId": 13,
        "qcPicCnt": 21,
        "qcVideoCnt": 0
      },
      {
        "id": "267321",
        "mallType": "WD",
        "itemId": "7305776516",
        "title": "Rep Sports Shoe Collection (Minor Dirt is Normal) YHH06",
        "picUrl": "https://cdn.findqc.com/item/20241130/m43g3fe0_oqff.jpg",
        "price": "¥79.00",
        "toPrice": "$12.42",
        "status": "normal",
        "shopInfo": {
          "id": "1672216213",
          "name": "Crazy Koala",
          "logo": "https://si.geilicdn.com/shopedit1897196691-072e000001928fa9890e0a239646-unadjust_750_750.png?w=250&amp;h=250&amp;cp=1",
          "type": "WD"
        },
        "categoryId": 13,
        "qcPicCnt": 155,
        "qcVideoCnt": 1
      },
      {
        "id": "182793",
        "mallType": "WD",
        "itemId": "7216590095",
        "title": "YC] Pure original foreign trade special price OW x N*K D*N*K LOW collection series",
        "picUrl": "https://cdn.findqc.com/item/20241118/m3mr79j1_gq9m.jpg",
        "price": "¥329.00",
        "toPrice": "$51.73",
        "status": "normal",
        "shopInfo": {
          "id": "1812255049",
          "name": "888VIP-SNKRS",
          "logo": "https://si.geilicdn.com/pcdecorate1816621089-76180000018cef01570f0a239737-unadjust_750_750.png?w=250&amp;h=250&amp;cp=1",
          "type": "WD"
        },
        "categoryId": 13,
        "qcPicCnt": 7,
        "qcVideoCnt": 0
      }
    ],
    "hasMore": true
  },
  "traceId": "2512021145071071916151093",
  "language": "en"
}