{
  "code": 20000,
  "name": "success",
  "message": "请求成功",
  "data": {
    "data": [
      {
        "id": "2450799",
        "mallType": "WD",
        "itemId": "7550190948",
        "title": "t-shirt",
        "picUrl": "https://si.geilicdn.com/open1762039621-252808396-1ce300000195bc1b3dd50a231226_800_800.jpg",
        "price": "¥97.00",
        "toPrice": "$15.25",
        "status": "normal",
        "shopInfo": {
          "id": "1794541533",
          "name": "1:1A&amp;V",
          "logo": "https://si.geilicdn.com/vshop-shop-logo-default.jpg?w=250&amp;h=250&amp;cp=1",
          "type": "WD"
        },
        "categoryId": 0,
        "qcPicCnt": 0,
        "qcVideoCnt": 0
      },
      {
        "id": "2450652",
        "mallType": "WD",
        "itemId": "7228757782",
        "title": "Summer fashion comfortable couple T-shirt PA 001-006 SYXDXXZLX001",
        "picUrl": "https://si.geilicdn.com/open1634031542-1234478995-5efe0000018e2ba81bac0a8133b5_1200_1200.jpg",
        "price": "¥99.00",
        "toPrice": "$15.57",
        "status": "normal",
        "shopInfo": {
          "id": "1634031542",
          "name": "PANDA KING SHOP",
          "logo": "https://si.geilicdn.com/shopedit1697417568-19920000018e46247ea20a2102d0-unadjust_750_750.png?w=250&amp;h=250&amp;cp=1",
          "type": "WD"
        },
        "categoryId": 0,
        "qcPicCnt": 0,
        "qcVideoCnt": 0
      },
      {
        "id": "2451067",
        "mallType": "TB",
        "itemId": "919747217137",
        "title": "Kanye West's Future Album Godscountry Archive Travisscott T-Shirt Hip Hop",
        "picUrl": "https://img.alicdn.com/bao/uploaded/i3/40937059/O1CN01EePf5z2214aSl3EIr_!!40937059.jpg",
        "price": "¥188.00",
        "toPrice": "$29.56",
        "status": "normal",
        "shopInfo": {
          "id": "33962959",
          "name": "DM衣设",
          "type": "TB"
        },
        "categoryId": 0,
        "qcPicCnt": 0,
        "qcVideoCnt": 0
      },
      {
        "id": "2450817",
        "mallType": "T1688",
        "itemId": "819952281856",
        "title": "2024 new melancholy rich second generation letters portrait printing loose casual short-sleeved T-shirt tide men and women models tide",
        "picUrl": "https://cbu01.alicdn.com/img/ibank/O1CN01PcMwGk297foqkWMaq_!!2210632468021-0-cib.jpg",
        "price": "¥51.00",
        "toPrice": "$8.02",
        "status": "normal",
        "shopInfo": {
          "id": "2210632468021",
          "name": "商丘冰王商贸有限公司",
          "type": "T1688"
        },
        "categoryId": 0,
        "qcPicCnt": 0,
        "qcVideoCnt": 0
      },
      {
        "id": "2451184",
        "mallType": "TB",
        "itemId": "643679868355",
        "title": "Playboi Carti Two-Dimensional Retro European and American High Street Black T-Shirt Hip-Hop Rap Unisex Short-Sleeved Loose Trendy Brand",
        "picUrl": "https://img.alicdn.com/bao/uploaded/i2/4065391552/O1CN015VGbCW1NKrN4m4m0u_!!0-item_pic.jpg",
        "price": "¥68.00",
        "toPrice": "$10.69",
        "status": "normal",
        "shopInfo": {
          "id": "583990223",
          "name": "图凡尼旗舰店",
          "type": "TB"
        },
        "categoryId": 0,
        "qcPicCnt": 0,
        "qcVideoCnt": 0
      },
      {
        "id": "2451423",
        "mallType": "WD",
        "itemId": "7531206913",
        "title": "Y2KShort-SleevedPoloShirtT-ShirtPrintPatternTopsDarkGothicVintageSummerStreetWearTopsHH",
        "picUrl": "https://cdn.findqc.com/item/20251026/mh6wgqj9_wm6o.jpg",
        "price": "¥71.24",
        "toPrice": "$11.20",
        "status": "normal",
        "shopInfo": {
          "id": "1785345597",
          "name": "Houston Store",
          "logo": "https://si.geilicdn.com/vshop-shop-logo-default.jpg?w=250&amp;h=250&amp;cp=1",
          "type": "WD"
        },
        "categoryId": 0,
        "qcPicCnt": 8,
        "qcVideoCnt": 0
      },
      {
        "id": "2451115",
        "mallType": "WD",
        "itemId": "7517082828",
        "title": "QLH09-Sports Pants Punching Jacket +86 19959480034",
        "picUrl": "https://si.geilicdn.com/open1737128957-1234478995-1a9d00000198127253110aa043f9_1200_1200.jpg",
        "price": "¥108.00",
        "toPrice": "$16.98",
        "status": "normal",
        "shopInfo": {
          "id": "1737128957",
          "name": "TOP High quality",
          "logo": "https://si.geilicdn.com/wdseller1970092633-061300000198991d28710a2396f4_250_250.jpg?w=250&amp;h=250&amp;cp=1",
          "type": "WD"
        },
        "categoryId": 0,
        "qcPicCnt": 0,
        "qcVideoCnt": 0
      },
      {
        "id": "2451171",
        "mallType": "WD",
        "itemId": "7437175207",
        "title": "DX23] Classic Letter Printed Short Sleeve T-Shirt for Men and Women Couple Dress",
        "picUrl": "https://si.geilicdn.com/open1687670541-252808396-67db00000195f54cd5810a8133b0_1200_1200.jpg",
        "price": "¥88.00",
        "toPrice": "$13.84",
        "status": "normal",
        "shopInfo": {
          "id": "1687670541",
          "name": "Super-We",
          "logo": "https://si.geilicdn.com/pcdecorate901935424363-395c00000195e72bcda10a20e273-unadjust_626_626.png?w=250&amp;h=250&amp;cp=1",
          "type": "WD"
        },
        "categoryId": 0,
        "qcPicCnt": 0,
        "qcVideoCnt": 0
      },
      {
        "id": "2451632",
        "mallType": "TB",
        "itemId": "714908254642",
        "title": "Peach Blossom Short Sleeve Butterfly Antisocialsocialclub Cherry Blossom Summer Couple pure cotton Short Sleeve T-Shirt Unisex",
        "picUrl": "https://img.alicdn.com/bao/uploaded/i3/892310821/O1CN01Xf3iX91Hw40HyFpjy_!!892310821.jpg",
        "price": "¥29.00",
        "toPrice": "$4.56",
        "status": "normal",
        "shopInfo": {
          "id": "73182498",
          "name": "柠檬绿茶mn的小店",
          "type": "TB"
        },
        "categoryId": 0,
        "qcPicCnt": 0,
        "qcVideoCnt": 0
      },
      {
        "id": "2450704",
        "mallType": "WD",
        "itemId": "7506049472",
        "title": "Stu22y Short Sleeve Style #202",
        "picUrl": "https://si.geilicdn.com/wdseller1965552696-684700000197ea7bc5d30a811411_1170_1170.jpg",
        "price": "¥59.00",
        "toPrice": "$9.28",
        "status": "normal",
        "shopInfo": {
          "id": "1616049789",
          "name": "ZS factory2",
          "logo": "https://si.geilicdn.com/wdseller1965552696-487e00000197e0b8acdf0a210139_250_250.jpg?w=250&amp;h=250&amp;cp=1",
          "type": "WD"
        },
        "categoryId": 0,
        "qcPicCnt": 0,
        "qcVideoCnt": 0
      },
      {
        "id": "2450948",
        "mallType": "WD",
        "itemId": "7469544284",
        "title": "QQX-1 24 Italy home and away soccer training jerseys co-branded version of the full range of soccer jerseys uniform wholesale undertake to send (first-class quality labels complete)",
        "picUrl": "https://si.geilicdn.com/pcitem1952305561-041300000196a48e76c70a2396f4_1200_1200.jpg",
        "price": "¥61.90",
        "toPrice": "$9.73",
        "status": "normal",
        "shopInfo": {
          "id": "1747108957",
          "name": "Roma Bella shoppe",
          "logo": "https://si.geilicdn.com/shopedit1952305561-6103000001969e6db09c0a20e7c7-unadjust_750_750.png?w=250&amp;h=250&amp;cp=1",
          "type": "WD"
        },
        "categoryId": 0,
        "qcPicCnt": 0,
        "qcVideoCnt": 0
      },
      {
        "id": "2450352",
        "mallType": "T1688",
        "itemId": "978024437050",
        "title": "Men's T-shirt summer casual men's comfortable soft polyester fabric speedway hot short sleeve",
        "picUrl": "https://cbu01.alicdn.com/img/ibank/O1CN01ncKjKj20cW1T0iTn0_!!2219641786870-0-cib.jpg",
        "price": "¥24.00",
        "toPrice": "$3.77",
        "status": "normal",
        "shopInfo": {
          "id": "2220526022480",
          "name": "上饶市瑾发服饰有限公司",
          "type": "T1688"
        },
        "categoryId": 0,
        "qcPicCnt": 0,
        "qcVideoCnt": 0
      },
      {
        "id": "1240466",
        "mallType": "TB",
        "itemId": "708688820105",
        "title": "Travis Scott Short-Sleeve Correct Version Ts Collaboration Same Style Utopia Limited Edition Hip-Hop American High Street T-Shirt Trendy",
        "picUrl": "https://img.alicdn.com/bao/uploaded/i3/2201440195721/O1CN01VVtSBW1s8GqjC28PO_!!2201440195721.jpg",
        "price": "¥101.64",
        "toPrice": "$15.98",
        "status": "normal",
        "shopInfo": {
          "id": "190175786",
          "name": "Beast欧美潮流",
          "type": "TB"
        },
        "categoryId": 0,
        "qcPicCnt": 185,
        "qcVideoCnt": 0
      },
      {
        "id": "1939721",
        "mallType": "T1688",
        "itemId": "902554799152",
        "title": "AMI & EANM Correct Edition Classic Small Love Embroidered Short-sleeved T-shirt Men's Summer Trendy Brand Loose Casual All-match T-shirt",
        "picUrl": "https://cbu01.alicdn.com/img/ibank/O1CN013hV5Kw1Rh5Ptou3GM_!!2217560922142-0-cib.jpg",
        "price": "¥34.90",
        "toPrice": "$5.49",
        "status": "normal",
        "shopInfo": {
          "id": "BBBoCztABgf8qyBRdI8vc321w",
          "name": "上饶市禄瑶电子商务有限公司",
          "type": "T1688"
        },
        "categoryId": 0,
        "qcPicCnt": 72,
        "qcVideoCnt": 0
      },
      {
        "id": "2196122",
        "mallType": "T1688",
        "itemId": "796315263827",
        "title": "Ximengyao Majira 24SS new 520 limited edition letter printed short sleeved men's and women's loose T-shirt summer trend",
        "picUrl": "https://cbu01.alicdn.com/img/ibank/O1CN01OR9WIa2GYQF6mW44F_!!2217877049027-0-cib.jpg",
        "price": "¥65.00",
        "toPrice": "$10.22",
        "status": "normal",
        "shopInfo": {
          "id": "BBBcrqIbd_lqzmodLNlceKlFg",
          "name": "常州宇选电子商务有限公司",
          "type": "T1688"
        },
        "categoryId": 0,
        "qcPicCnt": 8,
        "qcVideoCnt": 0
      },
      {
        "id": "1676384",
        "mallType": "TB",
        "itemId": "927075675710",
        "title": "JHXDF #PRO010 MON x Palm T-Shirt Coconut Tee",
        "picUrl": "https://img.alicdn.com/bao/uploaded/i4/2219842226979/O1CN019ZjzUM21QRCVl0m5f_!!2219842226979.jpg",
        "price": "¥85.00",
        "toPrice": "$13.37",
        "status": "normal",
        "shopInfo": {
          "id": "549752844",
          "name": "CoCoBiu",
          "type": "TB"
        },
        "categoryId": 0,
        "qcPicCnt": 8,
        "qcVideoCnt": 0
      },
      {
        "id": "1136386",
        "mallType": "TB",
        "itemId": "652921533523",
        "title": "European and American Oversized Ice Hockey Hip-Hop Couple Hip-Hop Bboy Jersey Teal Shark T-Shirt Long-Sleeved Plus-Size Trendy Clothing",
        "picUrl": "https://img.alicdn.com/bao/uploaded/i2/783090009/O1CN0178oDdi1BwAGMGVtNa_!!783090009.jpg",
        "price": "¥38.87",
        "toPrice": "$6.11",
        "status": "normal",
        "shopInfo": {
          "id": "101438338",
          "name": "凌子球衣Show",
          "type": "TB"
        },
        "categoryId": 0,
        "qcPicCnt": 18,
        "qcVideoCnt": 0
      },
      {
        "id": "3026779",
        "mallType": "TB",
        "itemId": "937499309108",
        "title": "American high street creative splicing color blocking badge short sleeved street hip-hop unisex loose casual T-shirt for summer",
        "picUrl": "https://img.alicdn.com/bao/uploaded/i1/2247438892/O1CN01SF4ozf2FYasWGGg53_!!2247438892.jpg",
        "price": "¥108.29",
        "toPrice": "$17.03",
        "status": "normal",
        "shopInfo": {
          "id": "254401958",
          "name": "33 TRENTE",
          "type": "TB"
        },
        "categoryId": 0,
        "qcPicCnt": 4,
        "qcVideoCnt": 0
      },
      {
        "id": "2572482",
        "mallType": "WD",
        "itemId": "7562517833",
        "title": "CPZCZPZ New Autumn Fashion Hundred Round Neck Sweatshirt-078",
        "picUrl": "https://si.geilicdn.com/pcitem901972474535-262e000001990974213c0a2301b4_1440_1440.jpg",
        "price": "¥127.00",
        "toPrice": "$19.97",
        "status": "normal",
        "shopInfo": {
          "id": "1830889667",
          "name": "ZAREL",
          "logo": "https://si.geilicdn.com/pcdecorate1967543857-635700000199939bccf00a2102c5-unadjust_750_750.png?w=250&amp;h=250&amp;cp=1",
          "type": "WD"
        },
        "categoryId": 0,
        "qcPicCnt": 12,
        "qcVideoCnt": 0
      },
      {
        "id": "1243418",
        "mallType": "T1688",
        "itemId": "676398072932",
        "title": "Foreign trade wholesale Alcatraz basic series short-sleeved phantom letters Logo printing T-shirt summer crowd couples clothing",
        "picUrl": "https://cbu01.alicdn.com/img/ibank/O1CN01JwwT4u1MRuCFnoZNZ_!!2210988121432-0-cib.jpg",
        "price": "¥45.00",
        "toPrice": "$7.08",
        "status": "normal",
        "categoryId": 0,
        "qcPicCnt": 41,
        "qcVideoCnt": 0
      }
    ],
    "hasMore": true
  },
  "traceId": "2512021141440801911211550",
  "language": "en"
}