{
  "code": 20000,
  "name": "success",
  "message": "请求成功",
  "data": {
    "data": [
      {
        "id": "2781040",
        "mallType": "WD",
        "itemId": "7576674073",
        "title": "Long Sleeve T-Shirt 10054011054-XW-1",
        "picUrl": "https://si.geilicdn.com/open1620179513-252808396-26b30000018f43a7cd470a8115b5_1080_1080.jpg",
        "price": "¥143.00",
        "toPrice": "$22.49",
        "status": "normal",
        "shopInfo": {
          "id": "1661917917",
          "name": "我的小店",
          "logo": "https://si.geilicdn.com/vshop-shop-logo-default.jpg?w=250&amp;h=250&amp;cp=1",
          "type": "WD"
        },
        "categoryId": 0,
        "qcPicCnt": 4,
        "qcVideoCnt": 0
      },
      {
        "id": "1947735",
        "mallType": "T1688",
        "itemId": "778864091571",
        "title": "Casablanca Casablanca summer new square gradient letters logo printing cotton short sleeve T-shirt",
        "picUrl": "https://cbu01.alicdn.com/img/ibank/O1CN01PnZmi72C3xQ4xW8UC_!!2206818368419-0-cib.jpg",
        "price": "¥62.00",
        "toPrice": "$9.75",
        "status": "normal",
        "shopInfo": {
          "id": "2206818368419",
          "name": "深圳市宝安区猿倍普服饰批发商行",
          "type": "T1688"
        },
        "categoryId": 0,
        "qcPicCnt": 56,
        "qcVideoCnt": 0
      },
      {
        "id": "3170198",
        "mallType": "T1688",
        "itemId": "879141757650",
        "title": "2025春夏新款 OW 大字母图案圆领套头短袖男女同款一件批发代发",
        "picUrl": "https://cbu01.alicdn.com/img/ibank/O1CN01aRwOtU1TjUiO6atzx_!!2208944992418-0-cib.jpg",
        "price": "¥54.00",
        "toPrice": "$8.49",
        "status": "normal",
        "shopInfo": {
          "id": "2208944992418",
          "name": "深圳市宝安区绣屿服装商行",
          "type": "T1688"
        },
        "categoryId": 0,
        "qcPicCnt": 27,
        "qcVideoCnt": 0
      },
      {
        "id": "3098368",
        "mallType": "T1688",
        "itemId": "879175297076",
        "title": "2025春夏新款 OW 巨鳄箭头图案圆领套头短袖男女同款一件批代发",
        "picUrl": "https://cbu01.alicdn.com/img/ibank/O1CN01KvUTdd1TjUiSRAiKq_!!2208944992418-0-cib.jpg",
        "price": "¥73.00",
        "toPrice": "$11.48",
        "status": "normal",
        "shopInfo": {
          "id": "2208944992418",
          "name": "深圳市宝安区绣屿服装商行",
          "type": "T1688"
        },
        "categoryId": 0,
        "qcPicCnt": 8,
        "qcVideoCnt": 0
      },
      {
        "id": "2574785",
        "mallType": "WD",
        "itemId": "7562900053",
        "title": "Full Moon Independent-ar7",
        "picUrl": "https://si.geilicdn.com/open1624782517-1624782517-0bdd000001987a5ff7c60a23b4de_1170_1222.jpg",
        "price": "¥74.00",
        "toPrice": "$11.64",
        "status": "normal",
        "shopInfo": {
          "id": "1716372755",
          "name": "BEST SHOP",
          "logo": "https://si.geilicdn.com/pcdecorate1995447126-57070000019998b2184a0a20e284-unadjust_750_750.png?w=250&amp;h=250&amp;cp=1",
          "type": "WD"
        },
        "categoryId": 0,
        "qcPicCnt": 4,
        "qcVideoCnt": 0
      },
      {
        "id": "1269118",
        "mallType": "T1688",
        "itemId": "898590035735",
        "title": "Foreign trade EU size RL summer polo shirt, men's short sleeved T-shirt, lapel, solid color pony embroidery casual wear, cross-border\n",
        "picUrl": "https://cbu01.alicdn.com/img/ibank/O1CN01SWXspl1CxNIhozbAR_!!2219422090147-0-cib.jpg",
        "price": "¥34.00",
        "toPrice": "$5.35",
        "status": "normal",
        "shopInfo": {
          "id": "BBBih8XcAUYWKYjRg_IgHyhCg",
          "name": "上饶市德谊电子商务有限公司",
          "type": "T1688"
        },
        "categoryId": 0,
        "qcPicCnt": 292,
        "qcVideoCnt": 0
      },
      {
        "id": "773303",
        "mallType": "T1688",
        "itemId": "785287421988",
        "title": "Cross-border Croza Chrome Heart High Quality Double Yarn Pure Cotton Men's and Women's Printed Long Sleeve T-Shirt",
        "picUrl": "https://cdn.findqc.com/item/20250427/m9ywb28d_zsaz.jpg",
        "price": "¥69.00",
        "toPrice": "$10.85",
        "status": "normal",
        "shopInfo": {
          "id": "BBBiNsxQtTkcsJvTUx3MIEjsA",
          "name": "深圳市龙华区库潮服饰批发商行",
          "type": "T1688"
        },
        "categoryId": 10,
        "qcPicCnt": 511,
        "qcVideoCnt": 9
      },
      {
        "id": "2451490",
        "mallType": "WD",
        "itemId": "7541696453",
        "title": "Basic letter classic logo slogan short sleeved men's and women's t-shirt - LMLSPTS0303",
        "picUrl": "https://si.geilicdn.com/open1668613661-1234478995-22b800000198370177820a23b491_800_800.jpg",
        "price": "¥56.00",
        "toPrice": "$8.81",
        "status": "normal",
        "shopInfo": {
          "id": "1835989667",
          "name": "我的小店",
          "logo": "https://si.geilicdn.com/vshop-shop-logo-default.jpg?w=250&amp;h=250&amp;cp=1",
          "type": "WD"
        },
        "categoryId": 0,
        "qcPicCnt": 4,
        "qcVideoCnt": 0
      },
      {
        "id": "271",
        "mallType": "TB",
        "itemId": "650330707151",
        "title": "Correct Version Travis Scott Collaboration Ps5 Crew Neck Short-Sleeve T-Shirt European and American Trendy Loose Lightning Dark Style",
        "picUrl": "https://cdn.findqc.com/item/20241118/m3m281ox_iqvi.jpg",
        "price": "¥50.84",
        "toPrice": "$7.99",
        "status": "normal",
        "shopInfo": {
          "id": "103318446",
          "name": "FFCP Studios",
          "type": "TB"
        },
        "categoryId": 10,
        "qcPicCnt": 523,
        "qcVideoCnt": 2
      },
      {
        "id": "1293487",
        "mallType": "T1688",
        "itemId": "905506088122",
        "title": "2025 early spring cross-border European and American foreign trade wholesale letter printing loose and simple casual high street couple short sleeved polo\n",
        "picUrl": "https://cbu01.alicdn.com/img/ibank/O1CN01NfR9AV1YVMZThyDZk_!!2215852093064-0-cib.jpg",
        "price": "¥45.00",
        "toPrice": "$7.08",
        "status": "normal",
        "shopInfo": {
          "id": "BBBOQtSezX_NU2pWMUWBoOZIw",
          "name": "广州粤正服装商行",
          "type": "T1688"
        },
        "categoryId": 0,
        "qcPicCnt": 8,
        "qcVideoCnt": 0
      },
      {
        "id": "1891689",
        "mallType": "TB",
        "itemId": "803374276885",
        "title": "Summer in Europe and the United States new tide brand cotton men and women couple paragraph T-shirt trend with short-sleeved loose big yards round neck male t",
        "picUrl": "https://img.alicdn.com/bao/uploaded/i1/2423619519/O1CN0125Tw9r2KBl6uOoobj_!!2423619519.jpg",
        "price": "¥35.90",
        "toPrice": "$5.65",
        "status": "normal",
        "shopInfo": {
          "id": "271225413",
          "name": "冰峰潮牌服装",
          "type": "TB"
        },
        "categoryId": 0,
        "qcPicCnt": 6,
        "qcVideoCnt": 0
      },
      {
        "id": "1665145",
        "mallType": "T1688",
        "itemId": "938539609610",
        "title": "Cross-Border Wholesale Dropshipping Ape Casual Round Neck Personalized Printed T-Shirts for Men and Women Couples Loose Short-Sleeved Camouflage Trendy Brand",
        "picUrl": "https://cbu01.alicdn.com/img/ibank/O1CN010gtLot1heMwHQCkiL_!!2218266314302-0-cib.jpg",
        "price": "¥45.00",
        "toPrice": "$7.08",
        "status": "normal",
        "shopInfo": {
          "id": "BBBL81wpaFiF6Fs5kQhkhno_w",
          "name": "广州潮疯街国际贸易商行",
          "type": "T1688"
        },
        "categoryId": 0,
        "qcPicCnt": 4,
        "qcVideoCnt": 0
      },
      {
        "id": "1379336",
        "mallType": "WD",
        "itemId": "7430351104",
        "title": "[DX19] Summer new cotton round neck short-sleeved men's T-shirt solid color casual fashion half-sleeved bottoming shirt-CY",
        "picUrl": "https://si.geilicdn.com/open1652813497-252808396-38bf00000190ab5af4380a239383_1920_1920.jpg",
        "price": "¥85.00",
        "toPrice": "$13.37",
        "status": "normal",
        "shopInfo": {
          "id": "1668172557",
          "name": "TOPSUMMER",
          "logo": "https://si.geilicdn.com/pcdecorate901935370638-6dde000001956ab6cb320a231316-unadjust_350_350.png?w=250&amp;h=250&amp;cp=1",
          "type": "WD"
        },
        "categoryId": 0,
        "qcPicCnt": 16,
        "qcVideoCnt": 0
      },
      {
        "id": "2845274",
        "mallType": "T1688",
        "itemId": "912353019792",
        "title": "Men's Summer Casual Sweat Absorbing Fashion Trend Simple Embroidered Pattern Printed Cotton T-Shirt",
        "picUrl": "https://cbu01.alicdn.com/img/ibank/O1CN015AVVFY1eJoIaF7TqI_!!2218691333851-0-cib.jpg",
        "price": "¥57.00",
        "toPrice": "$8.96",
        "status": "normal",
        "shopInfo": {
          "id": "BBB0Zci9RbA2dINpVxaH9CK6A",
          "name": "广州贝壳潮牌服饰商行",
          "type": "T1688"
        },
        "categoryId": 0,
        "qcPicCnt": 0,
        "qcVideoCnt": 0
      },
      {
        "id": "2844870",
        "mallType": "WD",
        "itemId": "7579970071",
        "title": "(Exclusive Welfare) Clothing length: 62, shoulder width: 43 with slight flaws, code: yz786. I agree to place an order without returning or exchanging!",
        "picUrl": "https://si.geilicdn.com/wdseller901921896855-259e0000019a0c9899460a2102c5_1179_1179.jpg",
        "price": "¥100.00",
        "toPrice": "$15.72",
        "status": "normal",
        "shopInfo": {
          "id": "1850717273",
          "name": "YOLO",
          "logo": "https://si.geilicdn.com/wdseller1845163825-643f0000018e441273ff0a21146b_250_250.jpg?w=250&amp;h=250&amp;cp=1",
          "type": "WD"
        },
        "categoryId": 0,
        "qcPicCnt": 0,
        "qcVideoCnt": 0
      },
      {
        "id": "2846941",
        "mallType": "TB",
        "itemId": "974512708213",
        "title": "Top Version! Paris Red Tape Distressed Long-Sleeve T-Shirt for Men and Women, Autumn and Winter 25Fw Loose Pure Cotton Base Shirt for Couples",
        "picUrl": "https://img.alicdn.com/bao/uploaded/i3/2495367023/O1CN01S5IhkB21kaerzqW44_!!2495367023.jpg",
        "price": "¥162.46",
        "toPrice": "$25.55",
        "status": "normal",
        "shopInfo": {
          "id": "120049375",
          "name": "Top Version",
          "type": "TB"
        },
        "categoryId": 0,
        "qcPicCnt": 4,
        "qcVideoCnt": 0
      },
      {
        "id": "2847003",
        "mallType": "WD",
        "itemId": "7510009614",
        "title": "[HB Self-made] Fog Cursive Letter Logo Printed Short Sleeve T 260G Combed Cotton Version to Version❗",
        "picUrl": "https://si.geilicdn.com/wdseller1391271756-421d00000198099738c10a2304a0_1276_1702.jpg",
        "price": "¥59.00",
        "toPrice": "$9.28",
        "status": "normal",
        "shopInfo": {
          "id": "1391271756",
          "name": "HB心动——做你的宝藏店铺",
          "logo": "https://si.geilicdn.com/bj-vshop-1391271756-1539962816810-1941450363_656_656.jpg?w=250&amp;h=250&amp;cp=1",
          "type": "WD"
        },
        "categoryId": 0,
        "qcPicCnt": 4,
        "qcVideoCnt": 0
      },
      {
        "id": "2844818",
        "mallType": "WD",
        "itemId": "7540999285",
        "title": "Long sleeved European and American suit, spicy girl shoulder single shoulder top, versatile half skirt, slightly revealing fashionable denim, iamgia * no quality issues, no reason for return",
        "picUrl": "https://si.geilicdn.com/open1769158365-252808396-47040000019914d784970a8115c2_800_800.jpg",
        "price": "¥187.18",
        "toPrice": "$29.43",
        "status": "normal",
        "shopInfo": {
          "id": "1769158365",
          "name": "GZ-made",
          "logo": "https://si.geilicdn.com/shopedit1956155466-1f3a00000197c5d2cba00a21146b-unadjust_750_750.png?w=250&amp;h=250&amp;cp=1",
          "type": "WD"
        },
        "categoryId": 0,
        "qcPicCnt": 0,
        "qcVideoCnt": 0
      },
      {
        "id": "2844979",
        "mallType": "TB",
        "itemId": "835838365643",
        "title": "[Bubble Home] Park Chan-Yeol Chanyeol Urban Scenery Dove Zate Dog House Baseball Uniform Hoodie",
        "picUrl": "https://img.alicdn.com/bao/uploaded/i1/800417791/O1CN01SHK1WI27QKpnfh91u_!!800417791.jpg",
        "price": "¥111.69",
        "toPrice": "$17.56",
        "status": "normal",
        "shopInfo": {
          "id": "378363855",
          "name": "泡泡家的店PaoPao",
          "type": "TB"
        },
        "categoryId": 0,
        "qcPicCnt": 0,
        "qcVideoCnt": 0
      }
    ],
    "hasMore": true
  },
  "traceId": "2512021141000182553894376",
  "language": "en"
}