{
  "code": 20000,
  "name": "success",
  "message": "请求成功",
  "data": {
    "data": [
      {
        "id": "2296787",
        "mallType": "T1688",
        "itemId": "899932280703",
        "title": "Goose down jacket Canada same style puff suit men and women couple bread clothes Parka coat jacket 2252MB",
        "picUrl": "https://cbu01.alicdn.com/img/ibank/O1CN01CVJr4N2AJruaiWdsh_!!2217010558183-0-cib.jpg",
        "price": "¥420.00",
        "toPrice": "$66.04",
        "status": "normal",
        "shopInfo": {
          "id": "2217010558183",
          "name": "莆田市城厢区艺玖大鹅服装商行（个体工商户）",
          "type": "T1688"
        },
        "categoryId": 0,
        "qcPicCnt": 4,
        "qcVideoCnt": 0
      },
      {
        "id": "3119295",
        "mallType": "T1688",
        "itemId": "836404645214",
        "title": "Crofton light 2229 down Vest vest geese for men and women",
        "picUrl": "https://cbu01.alicdn.com/img/ibank/O1CN01q9Nr9g1oPtf8bYDgq_!!2218522655218-0-cib.jpg",
        "price": "¥260.00",
        "toPrice": "$40.88",
        "status": "normal",
        "shopInfo": {
          "id": "BBBU4_Hyvr4OGyxe58zIVDO2A",
          "name": "莆田市秀屿区卡努服装店",
          "type": "T1688"
        },
        "categoryId": 0,
        "qcPicCnt": 24,
        "qcVideoCnt": 0
      },
      {
        "id": "3118168",
        "mallType": "WD",
        "itemId": "7583448196",
        "title": "01大鹅飞行员夹克男女冬季款三防毛领羽绒服情侣加厚户外工装",
        "picUrl": "https://si.geilicdn.com/open1622517075-1622517075-6c0f0000019a11844d050a23b491_800_1066.jpg",
        "price": "¥443.00",
        "toPrice": "$69.66",
        "status": "normal",
        "shopInfo": {
          "id": "1622517075",
          "name": "Janekrep",
          "logo": "https://si.geilicdn.com/pccreshp1999873750-6d8b00000199f23ea2530a20e7c7-unadjust_1024_1024.png?w=250&amp;h=250&amp;cp=1",
          "type": "WD"
        },
        "categoryId": 0,
        "qcPicCnt": 321,
        "qcVideoCnt": 0
      },
      {
        "id": "2420189",
        "mallType": "T1688",
        "itemId": "976423589711",
        "title": "Cross border QR code scanning Ralph RL men's and women's pony embroidered hooded detachable windproof, waterproof, warm cotton jacket",
        "picUrl": "https://cbu01.alicdn.com/img/ibank/O1CN01p4m3Yd1qq7feXC4kD_!!2220332635546-0-cib.jpg",
        "price": "¥135.00",
        "toPrice": "$21.23",
        "status": "normal",
        "shopInfo": {
          "id": "BBBDbXuiOZjv4QMWVMj5xsDfA",
          "name": "泉州市丰泽区墨驰服装商行",
          "type": "T1688"
        },
        "categoryId": 0,
        "qcPicCnt": 27,
        "qcVideoCnt": 0
      },
      {
        "id": "2427112",
        "mallType": "WD",
        "itemId": "7544388305",
        "title": "G78 K * a * di * n Softshell Jacket Kart",
        "picUrl": "https://si.geilicdn.com/pcitem1329468934-64fd000001992aba580c0a811411-unadjust_604_520.png",
        "price": "¥350.00",
        "toPrice": "$55.04",
        "status": "normal",
        "shopInfo": {
          "id": "1329468934",
          "name": "DreamRemake2",
          "logo": "https://si.geilicdn.com/shopedit1329468934-062100000197bafb32870a20e7c7-unadjust_89_89.png?w=250&amp;h=250&amp;cp=1",
          "type": "WD"
        },
        "categoryId": 0,
        "qcPicCnt": 4,
        "qcVideoCnt": 0
      },
      {
        "id": "2400438",
        "mallType": "WD",
        "itemId": "7526082694",
        "title": "Discounted price [7 days free return package] Canscan",
        "picUrl": "https://si.geilicdn.com/open1801180035-1234478995-7fc0000001989f1871ac0aa043f9_750_750.jpg",
        "price": "¥448.00",
        "toPrice": "$70.45",
        "status": "normal",
        "shopInfo": {
          "id": "1801180035",
          "name": "Luxereps",
          "logo": "https://si.geilicdn.com/wdseller1975786370-27cb000001984138b9680a23041a_250_250.jpg?w=250&amp;h=250&amp;cp=1",
          "type": "WD"
        },
        "categoryId": 0,
        "qcPicCnt": 4,
        "qcVideoCnt": 0
      },
      {
        "id": "1586395",
        "mallType": "T1688",
        "itemId": "923253262622",
        "title": "MAYA JACKET breadwear Mengjia Maya down jacket men and women with the same style Eason Chan the same style Mengkou",
        "picUrl": "https://cbu01.alicdn.com/img/ibank/O1CN01urOC8k1c9cBtlghoR_!!2218532613558-0-cib.jpg",
        "price": "¥380.00",
        "toPrice": "$59.75",
        "status": "normal",
        "shopInfo": {
          "id": "2219760993764",
          "name": "东莞大朗馨绒服装厂（个体工商户）",
          "type": "T1688"
        },
        "categoryId": 0,
        "qcPicCnt": 28,
        "qcVideoCnt": 0
      },
      {
        "id": "1137071",
        "mallType": "TB",
        "itemId": "846022809910",
        "title": "Ceiling David's Co-Branded Jo Series Week7 Puffer Embroidered Drawstring Soft Fur Collar down Jacket Couple Style",
        "picUrl": "https://img.alicdn.com/bao/uploaded/i1/3438180108/O1CN01rVRPoY1CfVmBHOnqC_!!3438180108.jpg",
        "price": "¥641.58",
        "toPrice": "$100.89",
        "status": "normal",
        "shopInfo": {
          "id": "273686414",
          "name": "DavidのNicola",
          "type": "TB"
        },
        "categoryId": 0,
        "qcPicCnt": 4,
        "qcVideoCnt": 0
      },
      {
        "id": "498342",
        "mallType": "WD",
        "itemId": "7328227154",
        "title": "[Newly added gray blue] Lightweight functional down jacket goose down version for both men and women, couple style, glossy version, shipped (4 styles to be distinguished)\n",
        "picUrl": "https://si.geilicdn.com/wdseller1428182270-14dc0000019aa46ef8450a23b4f4_1280_1280.jpg",
        "price": "¥380.00",
        "toPrice": "$59.75",
        "status": "normal",
        "shopInfo": {
          "id": "1750692064",
          "name": "愤怒的蓝弟弟999",
          "logo": "https://si.geilicdn.com/wdseller1428182270-3ce800000178d3af3b520a21c2a8_250_250.jpg?w=250&amp;h=250&amp;cp=1",
          "type": "WD"
        },
        "categoryId": 0,
        "qcPicCnt": 4,
        "qcVideoCnt": 0
      },
      {
        "id": "2734599",
        "mallType": "WD",
        "itemId": "7299967525",
        "title": "Down jacket 23",
        "picUrl": "https://si.geilicdn.com/pcitem1904699878-4739000001930b1481140a8133cc_1660_1276.jpg",
        "price": "¥568.00",
        "toPrice": "$89.32",
        "status": "normal",
        "shopInfo": {
          "id": "1809431509",
          "name": "all buy-cloth",
          "logo": "https://si.geilicdn.com/shopedit1904699878-1302000001931b722a4e0a23038e-unadjust_750_750.png?w=250&amp;h=250&amp;cp=1",
          "type": "WD"
        },
        "categoryId": 0,
        "qcPicCnt": 4,
        "qcVideoCnt": 0
      },
      {
        "id": "2744665",
        "mallType": "WD",
        "itemId": "7571599944",
        "title": "High quality winter fashion down jacket-001",
        "picUrl": "https://si.geilicdn.com/pcitem1450060287-5de300000198b88d32900a20e273_640_640.jpg",
        "price": "¥268.00",
        "toPrice": "$42.14",
        "status": "normal",
        "shopInfo": {
          "id": "1683326739",
          "name": "Kinetic Styles",
          "logo": "https://si.geilicdn.com/pcdecorate1996143018-2c6400000199a98feec00a20e284-unadjust_750_750.png?w=250&amp;h=250&amp;cp=1",
          "type": "WD"
        },
        "categoryId": 0,
        "qcPicCnt": 0,
        "qcVideoCnt": 0
      },
      {
        "id": "2751641",
        "mallType": "WD",
        "itemId": "7572515390",
        "title": "ES07-Classic versatile fashion down jacket collection-whatsapp+13256727890",
        "picUrl": "https://si.geilicdn.com/pcitem212547712-505900000198a7c356a10a210139_800_800.jpg",
        "price": "¥245.00",
        "toPrice": "$38.53",
        "status": "normal",
        "shopInfo": {
          "id": "1851626147",
          "name": "BLUEISLE",
          "logo": "https://si.geilicdn.com/pcdecorate1985913838-77bc0000019aa6849fdf0a239846-unadjust_750_750.png?w=250&amp;h=250&amp;cp=1",
          "type": "WD"
        },
        "categoryId": 0,
        "qcPicCnt": 0,
        "qcVideoCnt": 0
      },
      {
        "id": "2735090",
        "mallType": "WD",
        "itemId": "7551246990",
        "title": "Cotton Jacket",
        "picUrl": "https://si.geilicdn.com/open1854641997-252808396-20ba00000199483202f50a231226_1760_1760.jpg",
        "price": "¥559.00",
        "toPrice": "$87.90",
        "status": "normal",
        "shopInfo": {
          "id": "1854641997",
          "name": "Super shop",
          "logo": "https://si.geilicdn.com/shopedit1927964658-714c00000194c9d7ef590a2102c5-unadjust_750_750.png?w=250&amp;h=250&amp;cp=1",
          "type": "WD"
        },
        "categoryId": 0,
        "qcPicCnt": 0,
        "qcVideoCnt": 0
      },
      {
        "id": "2535911",
        "mallType": "WD",
        "itemId": "7543325309",
        "title": "C Uh Down Jacket - Popular Collection",
        "picUrl": "https://si.geilicdn.com/pcitem1806818931-114c00000191d1f580db0a20e7c7_800_800.jpg",
        "price": "¥209.00",
        "toPrice": "$32.86",
        "status": "normal",
        "shopInfo": {
          "id": "1684819651",
          "name": "Noble",
          "logo": "https://si.geilicdn.com/wdseller1980582729-4c97000001996bddbb3f0a2396f4_250_250.jpg?w=250&amp;h=250&amp;cp=1",
          "type": "WD"
        },
        "categoryId": 0,
        "qcPicCnt": 24,
        "qcVideoCnt": 0
      },
      {
        "id": "2751371",
        "mallType": "T1688",
        "itemId": "825965736065",
        "title": "2024 new 700 north family goose down down jacket 1996 models men and women with the same glossy American version of the jacket",
        "picUrl": "https://cbu01.alicdn.com/img/ibank/O1CN01HWDHAy1I8QqRDVyGN_!!2218423490848-0-cib.jpg",
        "price": "¥385.00",
        "toPrice": "$60.54",
        "status": "normal",
        "shopInfo": {
          "id": "2218423490848",
          "name": "莆田市秀屿区瑞达兴服饰店（个体工商户）",
          "type": "T1688"
        },
        "categoryId": 0,
        "qcPicCnt": 0,
        "qcVideoCnt": 0
      },
      {
        "id": "179829",
        "mallType": "WD",
        "itemId": "5625933471",
        "title": "1996 Down Cotton Jacket Eight colors (black, gray, navy blue, orange, pink, olive green, camouflage, yellow).\nPure 80 down filling! Received cut open is not 80 down clothing white direct refund! Embroidered elephant legs, waterproof fabric, hidden hood and collar.",
        "picUrl": "https://cdn.findqc.com/item/20241118/m3mqdqqs_4cyf.jpg",
        "price": "¥89.00",
        "toPrice": "$13.99",
        "status": "normal",
        "shopInfo": {
          "id": "1728635702",
          "name": "杭州卡卡一手潮牌批发代发",
          "logo": "https://si.geilicdn.com/weidian1693137638-5024000001985f7f07750a230115_996_996.jpg?w=250&amp;h=250&amp;cp=1",
          "type": "WD"
        },
        "categoryId": 33,
        "qcPicCnt": 123,
        "qcVideoCnt": 12
      },
      {
        "id": "2838070",
        "mallType": "WD",
        "itemId": "7586780247",
        "title": "Montbell puff jacket",
        "picUrl": "https://si.geilicdn.com/wdseller901907944121-29ec0000019a73d0533c0a20e7c7_1169_1132.jpg",
        "price": "¥440.00",
        "toPrice": "$69.19",
        "status": "normal",
        "shopInfo": {
          "id": "507105153",
          "name": "Dragon",
          "logo": "https://si.geilicdn.com/wdseller507105153-19c1000001951ceded450a2395d6_250_250.jpg?w=250&amp;h=250&amp;cp=1",
          "type": "WD"
        },
        "categoryId": 33,
        "qcPicCnt": 31,
        "qcVideoCnt": 2
      },
      {
        "id": "796651",
        "mallType": "WD",
        "itemId": "7303204804",
        "title": "Crofton 2227 lightweight down",
        "picUrl": "https://si.geilicdn.com/pcitem1426725758-24f200000197a0f417b20a20e2c5_800_800.jpg",
        "price": "¥488.00",
        "toPrice": "$76.74",
        "status": "normal",
        "shopInfo": {
          "id": "1830345312",
          "name": "ClassicGoose",
          "logo": "https://si.geilicdn.com/wdseller1426725758-5aaa00000192c239236b0a23111a_250_250.jpg?w=250&amp;h=250&amp;cp=1",
          "type": "WD"
        },
        "categoryId": 23,
        "qcPicCnt": 164,
        "qcVideoCnt": 2
      },
      {
        "id": "355398",
        "mallType": "WD",
        "itemId": "7284601510",
        "title": "Down Goose",
        "picUrl": "https://cdn.findqc.com/item/20241222/m4yn3ozh_ffjl.jpg",
        "price": "¥588.00",
        "toPrice": "$92.46",
        "status": "normal",
        "shopInfo": {
          "id": "1622703461",
          "name": "Trendybrandsmallshop",
          "logo": "https://si.geilicdn.com/vshop-shop-logo-default.jpg?w=250&amp;h=250&amp;cp=1",
          "type": "WD"
        },
        "categoryId": 0,
        "qcPicCnt": 106,
        "qcVideoCnt": 0
      }
    ],
    "hasMore": true
  },
  "traceId": "2512021143083801916157713",
  "language": "en"
}